{
  "trial_id": 198,
  "config": {
    "model_type": "coxnet",
    "model_params": {
      "l1_ratio": 0.9501070695797903,
      "alpha_min_ratio": 0.07617122739944104,
      "n_alphas": 287,
      "max_iter": 16151,
      "tol": 7.649833097902961e-05
    },
    "seed": 1024,
    "cv_n_splits": 5,
    "cv_n_repeats": 10,
    "preprocessing_config": {
      "eps": 1e-06,
      "min_speed": 0.01,
      "max_hours": 9999.0
    }
  },
  "result": {
    "c_index": 0.9363779397151376,
    "mean_brier": 0.025772545097319865,
    "hybrid_score": 0.9628726003464173,
    "std_c_index": 0.003637384051073927,
    "std_mean_brier": 0.0007945918262673415,
    "std_hybrid": 0.0015505597069758706
  }
}